logger_generate/__init__.py
logger_generate/logger_generate.py
logger_generate-0.2.0.dist-info/LICENSE
logger_generate-0.2.0.dist-info/WHEEL
logger_generate-0.2.0.dist-info/METADATA
logger_generate-0.2.0.dist-info/RECORD
