Metadata-Version: 2.1
Name: logger-generate
Version: 0.2.0
Summary: 開箱即用的logger。 easy to generate logger.
Home-page: https://github.com/we684123/logger_generate
License: MIT
Keywords: logger,logging,generate
Author: we684123
Author-email: we684123@gmail.com
Requires-Python: >=3.8,<4.0
Classifier: License :: OSI Approved :: MIT License
Classifier: Programming Language :: Python :: 3
Classifier: Programming Language :: Python :: 3.10
Classifier: Programming Language :: Python :: 3.8
Classifier: Programming Language :: Python :: 3.9
Requires-Dist: coloredlogs (>=15.0.1,<16.0.0)
Project-URL: Bug Tracker, https://github.com/we684123/logger_generate/issues
Project-URL: Documentation, https://github.com/we684123/logger_generate
Project-URL: Repository, https://github.com/we684123/logger_generate
